docs_generator/Document.py
docs_generator/__init__.py
docs_generator/config.py
docs_generator/docs_generator.py
docs_generator/exporter.py
docs_generator/utils.py
docs_generator-0.1.7.dist-info/METADATA
docs_generator-0.1.7.dist-info/WHEEL
docs_generator-0.1.7.dist-info/top_level.txt
docs_generator-0.1.7.dist-info/RECORD
