Metadata-Version: 2.1
Name: docs-generator
Version: 0.1.7
Summary: A program which convert jupyter notebook to mkdocs
Home-page: https://github.com/sirily11/algorithms
Author: sirily11
Author-email: sirily1997@gmail.com
License: UNKNOWN
Platform: UNKNOWN
Requires-Dist: nbconvert
Requires-Dist: mkdocs
Requires-Dist: pyyaml
Requires-Dist: mkdocs-material
Requires-Dist: pytest
